aissemble_encrypt_policy/__init__.py
aissemble_encrypt_policy/data_encryption_policy.py
aissemble_encrypt_policy/data_encryption_policy_exception.py
aissemble_encrypt_policy/data_encryption_policy_manager.py
aissemble_encrypt_policy/encrypt_input/__init__.py
aissemble_encrypt_policy/encrypt_input/data_encryption_policy_input.py
aissemble_foundation_encryption_policy_python-1.12.1.dist-info/LICENSE
aissemble_foundation_encryption_policy_python-1.12.1.dist-info/METADATA
aissemble_foundation_encryption_policy_python-1.12.1.dist-info/WHEEL
aissemble_foundation_encryption_policy_python-1.12.1.dist-info/RECORD
